sre_yield/__init__.py
sre_yield/cachingseq.py
sre_yield/fastdivmod.py
sre_yield/tests/__init__.py
sre_yield/tests/test_anchors.py
sre_yield/tests/test_bigrange.py
sre_yield/tests/test_cachingseq.py
sre_yield/tests/test_fastdivmod.py
sre_yield/tests/test_slicing.py
sre_yield/tests/test_sre_yield.py
sre_yield/tests/test_sre_yield_slow.py
sre_yield-1.2.dist-info/LICENSE
sre_yield-1.2.dist-info/METADATA
sre_yield-1.2.dist-info/WHEEL
sre_yield-1.2.dist-info/entry_points.txt
sre_yield-1.2.dist-info/top_level.txt
sre_yield-1.2.dist-info/RECORD
