Metadata-Version: 1.1
Name: sre-yield
Version: 1.2
Summary: Expands a regular expression to its possible matches
Home-page: https://github.com/google/sre_yield
Author: Alex Perry
Author-email: alex.perry@google.com
License: Apache
Platform: UNKNOWN
Classifier: License :: OSI Approved :: Apache Software License
Classifier: Intended Audience :: Developers
Classifier: Development Status :: 5 - Production/Stable
Classifier: Operating System :: OS Independent
